{"Title": "Amboy Solid Wood King Size Bed in Brown Red Finish", "Price": "25,499", "Details": {"Brand:": "Woodsworth", "Dimensions:": "H 31.5 x W 72 x D 78; Seating Height - 15 (All Dimensions in Inches)", "Weight:": "45 KG", "Warranty:": "36 Months' Warranty", "Assembly:": "Carpenter Assembly", "Primary Material:": "Acacia Wood", "Room Type:": "Bedroom", "Storage:": "No Storage", "Seating Height:": "15", "Recommended Mattress Size:": "78 L x 72 W Inch", "Sku:": "FM1816415-S-WH33805"}, "Description": "Woodsworth is our premium homegrown label that?s part classic, part contemporary. A delectable amalgamation of the timeless and trendy, a precarious balance of function and flair. Woodsworth is a harmonious fit for all tastes, styles and spaces. Contemporary ? is very current and in trend, of the here and now. It?s a very fluid style which takes its cues from the in vogue polishes, textures and colours of the season and bereft of any ornamentation or embellishments.  Furniture bought on Pepperfry.com comes with a 3 Year Warranty against any manufacturing defects. So go ahead and buy with confidence."}