{"Title": "Acropolis Solid Wood Chest of Drawers in Provincial Teak Finish", "Price": "27,999", "Details": {"Brand:": "Woodsworth", "Dimensions:": "H 34 x W 33 x D 16", "Weight:": "(all dimensions in inches)", "Colour:": "45 KG", "Warranty:": "Provincial Teak", "Assembly:": "36 Months' Warranty", "Primary Material:": "No Assembly Required", "Room Type:": "Sheesham Wood", "Collection:": "Bedroom", "Sku:": "Acropolis"}, "Description": "Woodsworth is our premium homegrown label thats part classic, part contemporary. A delectable amalgamation of the timeless and trendy, a precarious balance of function and flair. Woodsworth is a harmonious fit for all tastes, styles and spaces. Modern is a distinct, defined style which originated in the early 1900s. It uses a combination of vinyl, steel, plastic, glass or wood having monochromatic colors and sleek silhouettes. Modern furniture lives at the intersection of clean lines and relaxed comfort accentuating form and function. A chest of drawers, also called a bureau, is a type of cabinet that has multiple parallel, horizontal drawers usually stacked one above another. Chests of drawers have traditionally been used for storing clothing, especially underwear, socks, and other items not normally hung in or otherwise stored in a closet. They are usually placed in a bedroom for this purpose but can actually be used to store anything that will fit inside.  Furniture bought on Pepperfry.com comes with a 3 Year Warranty against any manufacturing defects. So go ahead and buy with confidence."}