{"Title": "Madison 1 Seater Sofa in Grey Colour", "Price": "10,199", "Details": {"Brand:": "Trevi Furniture", "Dimensions:": "H 34  x W 29 x D 34 ; Seating Height: 18 (All dimensions are in inches)", "Weight:": "27 KG", "Warranty:": "12 Months' Warranty", "Assembly:": "Carpenter Assembly", "Primary Material:": "Fabric", "Room Type:": "Living Room", "Seating Height:": "18", "Sku:": "FN1842455-S-PM29923"}, "Description": "With Trevi Furniture you get nothing but the best. With advanced manufacturing facility, tight control on quality and cost, Trevi Furniture has been positioned as a trusted brand since two decades. Modern Style Sofas usually come in fixed back with cushions attached to the frame. They mostly come with minimal details & compact proportions. These sofas can be with or without arms."}